leesung02_github_io-0.2.0.dist-info/METADATA
leesung02_github_io-0.2.0.dist-info/WHEEL
leesung02_github_io-0.2.0.dist-info/licenses/LICENSE.txt
leesung02_github_io/__init__.py
leesung02_github_io-0.2.0.dist-info/RECORD
